Metadata-Version: 2.1
Name: my-cool-lib-PG
Version: 0.1.0
Summary: Super useful library
Home-page: UNKNOWN
Author: Petr Gregor (SDA)
Author-email: pe.gregor@gmail.com
License: GNU GPL
Platform: UNKNOWN
